lfmxtractplus/__init__.py
lfmxtractplus/export_data.py
lfmxtractplus-1.2.dist-info/AUTHORS
lfmxtractplus-1.2.dist-info/LICENSE
lfmxtractplus-1.2.dist-info/METADATA
lfmxtractplus-1.2.dist-info/WHEEL
lfmxtractplus-1.2.dist-info/top_level.txt
lfmxtractplus-1.2.dist-info/RECORD
