Metadata-Version: 2.1
Name: lfmxtractplus
Version: 1.2
Summary: lfmxtractplus is a library for extracting last.fm scrobbles along with spotify audio features for use with pandas
Home-page: https://github.com/madhan001/lfmxtractplus
Author: Madhan Balaji
Author-email: madhanbalaji2000@gmail.com
License: MIT
Platform: UNKNOWN
Classifier: Programming Language :: Python :: 3
Classifier: License :: OSI Approved :: MIT License
Classifier: Operating System :: OS Independent
Requires-Dist: PyYAML (>=5.1.1)
Requires-Dist: numpy (>=1.14.0)
Requires-Dist: pandas (>=0.22.0)
Requires-Dist: requests (>=2.22.0)
Requires-Dist: spotipy (>=2.4.4)
Requires-Dist: tqdm (>=4.31.1)
